endstone_essentials/__init__.py
endstone_essentials/config.toml
endstone_essentials/essentials_plugin.py
endstone_essentials/plugin.yml
endstone_essentials/commands/__init__.py
endstone_essentials/commands/back_command.py
endstone_essentials/commands/broadcast_command.py
endstone_essentials/commands/command_executor_base.py
endstone_essentials/commands/fly_command.py
endstone_essentials/commands/home_command.py
endstone_essentials/commands/notice_command.py
endstone_essentials/commands/ping_command.py
endstone_essentials/commands/tpa_command.py
endstone_essentials/commands/warp_command.py
endstone_essentials-0.0.5.dist-info/METADATA
endstone_essentials-0.0.5.dist-info/WHEEL
endstone_essentials-0.0.5.dist-info/entry_points.txt
endstone_essentials-0.0.5.dist-info/licenses/LICENSE
endstone_essentials-0.0.5.dist-info/RECORD
