Metadata-Version: 2.3
Name: endstone-essentials
Version: 0.0.5
Summary: The modern essentials suite for endstone server
Project-URL: Homepage, https://github.com/endstone-essentials/essentials
Author-email: daoge_cmd <3523206925@qq.com>, Vincent Wu <magicdroidx@gmail.com>
License:                    GNU LESSER GENERAL PUBLIC LICENSE
License-File: LICENSE
Keywords: endstone,essentials,plugin
Requires-Dist: pyyaml
